{
  "profile": [
    {
      "id": 1,
      "fname": "Arun",
      "lname": "menon",
      "email": "arun@gmail.com",
      "emprole": "front end developer",
      "age": 23,
      "dob": "1999-07-17",
      "gender": "male",
      "bloodgroup": "A+ve",
      "phone": 9388952169,
      "password": "Akshayanil16@",
      "confirmpassword": "Akshayanil16@",
      "img": "../assets/img/Profile-01.jpg",
      "noofleaves": 5,
      "leaveDates": [
        "2023-03-28T00:00:00.000Z",
        "2023-03-29T00:00:00.000Z",
        "2023-03-30T00:00:00.000Z",
        "2023-03-31T00:00:00.000Z"
      ],
      "leavereason": "Family Trip",
      "leavetype": "casual leave",
      "leavedaytype": "halfday",
      "leavefrom": "2023-03-29",
      "leaveto": "2023-03-31",
      "numberofdays": 3
    },
    {
      "fname": "manu",
      "lname": "k",
      "email": "manu@gmail.com",
      "emprole": "QA",
      "age": 22,
      "dob": "2000-01-12",
      "gender": "male",
      "bloodgroup": "AB+ve",
      "phone": 9388952169,
      "password": "Akshayanil16@",
      "confirmpassword": "Akshayanil16@",
      "img": "../assets/img/Profile-06.jpg",
      "id": 5,
      "noofleaves": 3,
      "leavereason": "Body pain",
      "leavetype": "sick leave",
      "leavedaytype": "halfday",
      "leavefrom": "2023-03-28",
      "leaveto": "2023-03-30",
      "numberofdays": 3
    },
    {
      "fname": "Rohit",
      "lname": "Sharma",
      "email": "rohit@gmail.com",
      "emprole": "Java Developer",
      "age": 23,
      "dob": "1998-06-31",
      "gender": "male",
      "bloodgroup": "AB-ve",
      "phone": 9846114534,
      "password": "Akshayanil16@",
      "confirmpassword": "Akshayanil16@",
      "img": "../assets/img/Profile-02.jpg",
      "id": 6,
      "noofleaves": null,
      "leaveDates": [
        "2023-03-29T00:00:00.000Z",
        "2023-03-30T00:00:00.000Z"
      ]
    },
    {
      "fname": "Peter",
      "lname": "kumar",
      "email": "prter@gmail.com",
      "emprole": "Nodejs Developer",
      "age": 25,
      "dob": "1998-06-10",
      "gender": "male",
      "bloodgroup": "AB-ve",
      "phone": 9887123456,
      "password": "Akshayanil16@",
      "confirmpassword": "Akshayanil16@",
      "img": "../assets/img/Profile-04.jpg",
      "id": 7
    },
    {
      "fname": "Nikhil",
      "lname": "Rane",
      "email": "nikhil@gmail.com",
      "emprole": "React Trainee",
      "age": 23,
      "dob": "1998-06-01",
      "gender": "male",
      "bloodgroup": "B+ve",
      "phone": 9934651785,
      "password": "Akshayanil16@",
      "confirmpassword": "Akshayanil16@",
      "img": "../assets/img/Profile-03.jpg",
      "id": 8,
      "noofleaves": 4,
      "leaveDates": [
        "2023-03-28T00:00:00.000Z",
        "2023-03-29T00:00:00.000Z",
        "2023-03-30T00:00:00.000Z",
        "2023-03-31T00:00:00.000Z"
      ],
      "leavereason": "Family Trip",
      "leavetype": "casual leave",
      "leavedaytype": "halfday",
      "leavefrom": "2023-03-29",
      "leaveto": "2023-03-31",
      "numberofdays": 3
    },
    {
      "fname": "Yash",
      "lname": "Menon",
      "email": "yash@gmail.com",
      "emprole": "Trainee",
      "age": 27,
      "dob": "1997-01-18",
      "gender": "male",
      "bloodgroup": "O-ve",
      "phone": 8913456879,
      "password": "Akshayanil16@",
      "confirmpassword": "Akshayanil16@",
      "img": "../assets/img/Profile-02.jpg",
      "id": 9
    },
    {
      "fname": "Pooja",
      "lname": "M",
      "email": "pooja@gmail.com",
      "emprole": "Trainee",
      "age": 24,
      "dob": "1999-02-11",
      "gender": "female",
      "bloodgroup": "AB-ve",
      "phone": 9962345612,
      "password": "Akshayanil16@",
      "confirmpassword": "Akshayanil16@",
      "img": "../assets/img/Profile-05.jpg",
      "id": 10
    },
    {
      "fname": "Ajay",
      "lname": "k",
      "email": "ajay@gmail.com",
      "emprole": "QA",
      "age": 30,
      "dob": "1993-03-28",
      "gender": "male",
      "bloodgroup": "AB-ve",
      "phone": 9961234565,
      "password": "Akshayanil16@",
      "confirmpassword": "Akshayanil16@",
      "img": "../assets/img/Profile-06.jpg",
      "id": 11
    },
    {
      "fname": "Prathamesh",
      "lname": "kumar",
      "email": "prathamesh@gmail.com",
      "emprole": "Tester",
      "age": 28,
      "dob": "1992-08-16",
      "gender": "male",
      "bloodgroup": "AB-ve",
      "phone": 9841785367,
      "password": "Akshayanil16@",
      "confirmpassword": "Akshayanil16@",
      "img": "../assets/img/Profile-04.jpg",
      "id": 12
    }
  ]
}